gestao_classificacoes/__init__.py
gestao_classificacoes/core.py
gestao_classificacoes-0.1.0.dist-info/LICENSE
gestao_classificacoes-0.1.0.dist-info/METADATA
gestao_classificacoes-0.1.0.dist-info/WHEEL
gestao_classificacoes-0.1.0.dist-info/top_level.txt
gestao_classificacoes-0.1.0.dist-info/RECORD
