Metadata-Version: 2.1
Name: gestao_classificacoes
Version: 0.1.0
Summary: Sistema de Gestão de Classificações de Alunos
Home-page: https://github.com/a041011/gestao_classificacoes
Author: Seu Nome
Author-email: seu.email@example.com
Classifier: Programming Language :: Python :: 3
Classifier: License :: OSI Approved :: MIT License
Classifier: Operating System :: OS Independent
Requires-Python: >=3.7
License-File: LICENSE
